myrest/__init__.py
myrest/myparser.py
myrest/myrestengine.py
myrest-0.1.10.dist-info/LICENSE
myrest-0.1.10.dist-info/METADATA
myrest-0.1.10.dist-info/WHEEL
myrest-0.1.10.dist-info/top_level.txt
myrest-0.1.10.dist-info/RECORD
