Metadata-Version: 2.1
Name: myrest
Version: 0.1.10
Summary: A RESTful wrapper for django project
Home-page: https://github.com/xiaoyexu/myrestengine
Author: Xiaoye Xu
Author-email: xiaoye.xu@outlook.com
License: UNKNOWN
Platform: UNKNOWN
Classifier: Programming Language :: Python :: 3.6
Classifier: Framework :: Django :: 1.9
Classifier: License :: OSI Approved :: MIT License
Requires-Dist: django (>=1.9.0)
